jaggu/__init__.py
Jaggu-0.0.13.dist-info/METADATA
Jaggu-0.0.13.dist-info/WHEEL
Jaggu-0.0.13.dist-info/top_level.txt
Jaggu-0.0.13.dist-info/RECORD
