Metadata-Version: 2.1
Name: Jaggu
Version: 0.0.13
Summary: Lulu
Home-page: UNKNOWN
Author: Anonymous
Author-email: mohammedfaisal3366@gmail.com
License: UNKNOWN
Keywords: python
Platform: UNKNOWN
Classifier: Development Status :: 1 - Planning
Classifier: Intended Audience :: Developers
Classifier: Programming Language :: Python :: 3
Classifier: Operating System :: Unix
Classifier: Operating System :: MacOS :: MacOS X
Classifier: Operating System :: Microsoft :: Windows
